cassidy/__init__.py
cassidy/models.py
cassidy/parsers.py
cassidy/renderers.py
cassidy/repositories.py
cassidy/styles.py
cassidy/translators.py
cassidy/types.py
cassidy/utils.py
cassidy-0.1.3.dist-info/LICENSE
cassidy-0.1.3.dist-info/WHEEL
cassidy-0.1.3.dist-info/METADATA
cassidy-0.1.3.dist-info/RECORD
